src/__init__.py
src/server.py
src/application/__init__.py
src/application/asset_service.py
src/application/document_service.py
src/application/job_service.py
src/application/knowledge_service.py
src/application/table_service.py
src/domain/__init__.py
src/domain/chunking.py
src/domain/entities.py
src/domain/image_processor.py
src/domain/job.py
src/domain/repositories.py
src/domain/services.py
src/domain/table_entities.py
src/domain/value_objects.py
src/infrastructure/__init__.py
src/infrastructure/config.py
src/infrastructure/excel_renderer.py
src/infrastructure/file_storage.py
src/infrastructure/job_store.py
src/infrastructure/lightrag_adapter.py
src/infrastructure/pdf_extractor.py
src/presentation/__init__.py
src/presentation/server.py
asset_aware_mcp-0.2.5.dist-info/METADATA
asset_aware_mcp-0.2.5.dist-info/WHEEL
asset_aware_mcp-0.2.5.dist-info/entry_points.txt
asset_aware_mcp-0.2.5.dist-info/licenses/LICENSE
asset_aware_mcp-0.2.5.dist-info/RECORD
