Metadata-Version: 2.4
Name: asset-aware-mcp
Version: 0.2.5
Summary: Medical RAG with Asset-Aware MCP - Precise PDF asset retrieval (tables, figures, sections) for AI Agents
Project-URL: Homepage, https://github.com/u9401066/asset-aware-mcp
Project-URL: Documentation, https://github.com/u9401066/asset-aware-mcp#readme
Project-URL: Repository, https://github.com/u9401066/asset-aware-mcp.git
Project-URL: Issues, https://github.com/u9401066/asset-aware-mcp/issues
Project-URL: Changelog, https://github.com/u9401066/asset-aware-mcp/blob/main/CHANGELOG.md
Author-email: u9401066 <u9401066@gap.kmu.edu.tw>
Maintainer-email: u9401066 <u9401066@gap.kmu.edu.tw>
License: Apache-2.0
License-File: LICENSE
Keywords: ai,document-processing,fastmcp,lightrag,llm,mcp,medical,pdf,rag
Classifier: Development Status :: 4 - Beta
Classifier: Intended Audience :: Developers
Classifier: Intended Audience :: Healthcare Industry
Classifier: Intended Audience :: Science/Research
Classifier: License :: OSI Approved :: Apache Software License
Classifier: Operating System :: OS Independent
Classifier: Programming Language :: Python :: 3
Classifier: Programming Language :: Python :: 3.10
Classifier: Programming Language :: Python :: 3.11
Classifier: Programming Language :: Python :: 3.12
Classifier: Topic :: Scientific/Engineering :: Artificial Intelligence
Classifier: Topic :: Scientific/Engineering :: Medical Science Apps.
Classifier: Topic :: Text Processing :: General
Classifier: Typing :: Typed
Requires-Python: >=3.10
Requires-Dist: aiofiles>=24.0.0
Requires-Dist: httpx>=0.28.1
Requires-Dist: lightrag-hku>=1.0.0
Requires-Dist: mcp>=1.0.0
Requires-Dist: mistralai>=1.0.0
Requires-Dist: pillow>=10.0.0
Requires-Dist: pydantic-settings>=2.12.0
Requires-Dist: pydantic>=2.0.0
Requires-Dist: pymupdf>=1.24.0
Requires-Dist: python-dotenv>=1.0.0
Requires-Dist: xlsxwriter>=3.2.9
Provides-Extra: dev
Requires-Dist: mypy>=1.13.0; extra == 'dev'
Requires-Dist: pytest-asyncio>=0.24.0; extra == 'dev'
Requires-Dist: pytest-cov>=5.0.0; extra == 'dev'
Requires-Dist: pytest>=8.0.0; extra == 'dev'
Requires-Dist: ruff>=0.8.0; extra == 'dev'
